mlworks/__init__.py
mlworks/engineering.py
tests/__init__.py
tests/test_engineering.py
mlworks-0.0.6.dist-info/LICENSE
mlworks-0.0.6.dist-info/METADATA
mlworks-0.0.6.dist-info/WHEEL
mlworks-0.0.6.dist-info/top_level.txt
mlworks-0.0.6.dist-info/RECORD
