Metadata-Version: 2.1
Name: mlworks
Version: 0.0.6
Summary: Python Package for Unlimited Machine Learning Works
Home-page: https://github.com/adelmofilho/mlworks
Author: Adelmo Filho
Author-email: adelmo.aguiar.filho@gmail.com
License: UNKNOWN
Keywords: mlworks,Python,projects,machine-learning,feature-engineering,modelling,data-science
Platform: UNKNOWN
Classifier: Programming Language :: Python :: 3 :: Only
Classifier: Programming Language :: Python :: 3
Classifier: Programming Language :: Python :: 3.6
Classifier: Programming Language :: Python :: 3.7
Classifier: Programming Language :: Python :: 3.8
Classifier: License :: OSI Approved :: MIT License
Classifier: Operating System :: OS Independent
Classifier: Development Status :: 1 - Planning
Classifier: Natural Language :: Portuguese (Brazilian)
Classifier: Topic :: Scientific/Engineering :: Artificial Intelligence
Requires-Python: >=3.6
Requires-Dist: numpy
Requires-Dist: pandas
